CHANGELOG.md
LICENSE.txt
MANIFEST.in
README.md
requirements-dev.txt
setup.cfg
setup.py
pydu/__init__.py
pydu/archive.py
pydu/cmd.py
pydu/compat.py
pydu/console.py
pydu/convert.py
pydu/dict.py
pydu/dt.py
pydu/environ.py
pydu/exception.py
pydu/functional.py
pydu/inspect.py
pydu/iter.py
pydu/list.py
pydu/misc.py
pydu/network.py
pydu/path.py
pydu/platform.py
pydu/process.py
pydu/request.py
pydu/set.py
pydu/slot.py
pydu/string.py
pydu/system.py
pydu/unit.py
pydu.egg-info/PKG-INFO
pydu.egg-info/SOURCES.txt
pydu.egg-info/dependency_links.txt
pydu.egg-info/top_level.txt
tests/__init__.py
tests/test_archive.py
tests/test_cmd.py
tests/test_compat.py
tests/test_console.py
tests/test_convert.py
tests/test_dict.py
tests/test_dt.py
tests/test_environ.py
tests/test_exception.py
tests/test_functional.py
tests/test_inspect.py
tests/test_iter.py
tests/test_list.py
tests/test_misc.py
tests/test_network.py
tests/test_path.py
tests/test_platform.py
tests/test_request.py
tests/test_set.py
tests/test_slot.py
tests/test_string.py
tests/test_system.py
tests/test_unit.py
tests/testing.py